cooSql/__init__.py
cooSql/error.py
cooSql/examples/README.md
cooSql/examples/__init__.py
cooSql/examples/__pycache__/__init__.cpython-313.pyc
cooSql/examples/basic_usage/__init__.py
cooSql/examples/basic_usage/batch_operations.db
cooSql/examples/basic_usage/batch_operations_test.py
cooSql/examples/basic_usage/crud_operations_example.py
cooSql/examples/basic_usage/disk_example.py
cooSql/examples/basic_usage/memory_example.py
cooSql/examples/basic_usage/multi_schema_example.py
cooSql/examples/basic_usage/persistence_example.db
cooSql/examples/basic_usage/persistence_example.py
cooSql/examples/basic_usage/transaction_example.py
cooSql/examples/basic_usage/__pycache__/__init__.cpython-313.pyc
cooSql/examples/basic_usage/__pycache__/batch_operations_test.cpython-313-pytest-7.4.4.pyc
cooSql/examples/basic_usage/__pycache__/data_consistency_example.cpython-313.pyc
cooSql/examples/basic_usage/__pycache__/disk_example.cpython-313.pyc
cooSql/examples/basic_usage/__pycache__/memory_example.cpython-313.pyc
cooSql/examples/basic_usage/__pycache__/transaction_example.cpython-313.pyc
cooSql/sql/__init__.py
cooSql/sql/schema.py
cooSql/sql/session.py
cooSql/sql/engine/__init__.py
cooSql/sql/engine/base.py
cooSql/sql/engine/kv.py
cooSql/sql/executor/__init__.py
cooSql/sql/executor/executor.py
cooSql/sql/parser/__init__.py
cooSql/sql/parser/ast.py
cooSql/sql/parser/lexer.py
cooSql/sql/parser/parser.py
cooSql/sql/plan/__init__.py
cooSql/sql/plan/plan.py
cooSql/sql/plan/planner.py
cooSql/sql/types/__init__.py
cooSql/sql/types/data_types.py
cooSql/storage/__init__.py
cooSql/storage/disk.py
cooSql/storage/engine.py
cooSql/storage/keycode.py
cooSql/storage/memory.py
cooSql/storage/mvcc.py
cooSql/tests/__init__.py
cooSql/tests/test_crud.py
cooSql/tests/test_lexer.py
cooSql/tests/test_parser.py
cooSql/tests/test_plan.py
cooSql/tests/test_sql_engine.py
cooSql/tests/__pycache__/__init__.cpython-313.pyc
cooSql/tests/__pycache__/test_crud.cpython-313-pytest-7.4.4.pyc
coosql-0.1.0.dist-info/licenses/LICENSE
coosql-0.1.0.dist-info/METADATA
coosql-0.1.0.dist-info/WHEEL
coosql-0.1.0.dist-info/top_level.txt
coosql-0.1.0.dist-info/RECORD
