Metadata-Version: 2.4
Name: cooSql
Version: 0.1.0
Summary: Python implementation of a lightweight SQL database system for educational purposes
Home-page: https://github.com/yourusername/cooSql
Author: cooSql Contributors
Author-email: your.email@example.com
License: MIT
Project-URL: Bug Tracker, https://github.com/yourusername/cooSql/issues
Project-URL: Documentation, https://github.com/yourusername/cooSql/blob/main/README.md
Project-URL: Source Code, https://github.com/yourusername/cooSql
Keywords: database,sql,education,learning,kv-store,lightweight-database
Classifier: Programming Language :: Python :: 3
Classifier: Programming Language :: Python :: 3.7
Classifier: Programming Language :: Python :: 3.8
Classifier: Programming Language :: Python :: 3.9
Classifier: Programming Language :: Python :: 3.10
Classifier: License :: OSI Approved :: MIT License
Classifier: Operating System :: OS Independent
Classifier: Topic :: Database
Classifier: Topic :: Education
Classifier: Topic :: Software Development :: Libraries
Classifier: Intended Audience :: Education
Classifier: Intended Audience :: Developers
Requires-Python: >=3.7
License-File: LICENSE
Requires-Dist: typing; python_version < "3.5"
Dynamic: author
Dynamic: author-email
Dynamic: classifier
Dynamic: description
Dynamic: description-content-type
Dynamic: home-page
Dynamic: keywords
Dynamic: license
Dynamic: license-file
Dynamic: project-url
Dynamic: requires-dist
Dynamic: requires-python
Dynamic: summary
